rstr_max/__about__.py
rstr_max/__init__.py
rstr_max/cli.py
rstr_max/main.py
rstr_max-0.0.6.dist-info/METADATA
rstr_max-0.0.6.dist-info/WHEEL
rstr_max-0.0.6.dist-info/entry_points.txt
rstr_max-0.0.6.dist-info/licenses/LICENSE.txt
rstr_max-0.0.6.dist-info/RECORD
